chercher/__init__.py
chercher/app.py
chercher/cli.py
chercher/db.py
chercher/db_actions.py
chercher/hookspecs.py
chercher/models.py
chercher/output.py
chercher/plugin_manager.py
chercher/settings.py
chercher/styles.tcss
chercher/utils.py
chercher-0.1.38.dist-info/METADATA
chercher-0.1.38.dist-info/WHEEL
chercher-0.1.38.dist-info/entry_points.txt
chercher-0.1.38.dist-info/RECORD
